infi.winver-1.0.3-py2.7-nspkg.pth
infi/winver/__init__.py
infi/winver/__version__.py
infi/winver/constants.py
infi/winver/interface.py
infi/winver/scripts.py
infi/winver/structures.py
infi/winver/tests.py
infi.winver-1.0.3.dist-info/LICENSE
infi.winver-1.0.3.dist-info/METADATA
infi.winver-1.0.3.dist-info/WHEEL
infi.winver-1.0.3.dist-info/entry_points.txt
infi.winver-1.0.3.dist-info/namespace_packages.txt
infi.winver-1.0.3.dist-info/top_level.txt
infi.winver-1.0.3.dist-info/RECORD
